{"TEST.0": {"timed": 0, "count": 50, "questions": [1, 2, 3, 4, 5, 6, 7, 8, 9, 10, 11, 12, 13, 14, 15, 16, 17, 18, 19, 20, 21, 22, 23, 24, 25, 26, 27, 28, 29, 30, 31, 32, 33, 34, 35, 36, 37, 38, 39, 40, 41, 42, 43, 44, 45, 46, 47, 48, 49, 50], "title": "aristoSpam", "useCustomHeader": false, "customHeader": "", "testtype": "cstate"}, "CIPHER.0": {"cipherString": "Great men are like eagles, and build their nest on some lofty solitude.", "encodeType": "random", "offset": 1, "shift": 1, "offset2": 1, "keyword": "", "keyword2": "", "alphabetSource": "ABCDEFGHIJKLMNOPQRSTUVWXYZ", "alphabetDest": "EIXCTVJPMNAHQRLGFWOYKBUZDS", "curlang": "en", "replacement": {"A": "E", "B": "I", "C": "X", "D": "C", "E": "T", "F": "V", "G": "J", "H": "P", "I": "M", "J": "N", "K": "A", "L": "H", "M": "Q", "N": "R", "O": "L", "P": "G", "Q": "F", "R": "W", "S": "O", "T": "Y", "U": "K", "V": "B", "W": "U", "X": "Z", "Y": "D", "Z": "S"}, "editEntry": "0", "cipherType": "aristocrat", "question": "<p>Solve this aristocrat.</p>", "points": 250}, "CIPHER.1": {"cipherString": "I object to violence because when it appears to do good, the good is only temporary; the evil it does is permanent.", "encodeType": "random", "offset": 1, "shift": 1, "offset2": 1, "keyword": "", "keyword2": "", "alphabetSource": "ABCDEFGHIJKLMNOPQRSTUVWXYZ", "alphabetDest": "DCWQJMZLOGHXVEUIYPFARTNBSK", "curlang": "en", "replacement": {"A": "D", "B": "C", "C": "W", "D": "Q", "E": "J", "F": "M", "G": "Z", "H": "L", "I": "O", "J": "G", "K": "H", "L": "X", "M": "V", "N": "E", "O": "U", "P": "I", "Q": "Y", "R": "P", "S": "F", "T": "A", "U": "R", "V": "T", "W": "N", "X": "B", "Y": "S", "Z": "K"}, "editEntry": "0", "cipherType": "aristocrat", "question": "<p>Solve this aristocrat.</p>", "points": 250}, "CIPHER.2": {"cipherString": "The influence of a science adviser is only as good as ears open to that science advice.", "encodeType": "random", "offset": 1, "shift": 1, "offset2": 1, "keyword": "", "keyword2": "", "alphabetSource": "ABCDEFGHIJKLMNOPQRSTUVWXYZ", "alphabetDest": "FZNIALJWROQMPECVHXTSBYGUKD", "curlang": "en", "replacement": {"A": "F", "B": "Z", "C": "N", "D": "I", "E": "A", "F": "L", "G": "J", "H": "W", "I": "R", "J": "O", "K": "Q", "L": "M", "M": "P", "N": "E", "O": "C", "P": "V", "Q": "H", "R": "X", "S": "T", "T": "S", "U": "B", "V": "Y", "W": "G", "X": "U", "Y": "K", "Z": "D"}, "editEntry": "1", "cipherType": "aristocrat", "question": "<p>Solve this aristocrat.</p>", "points": 250}, "CIPHER.3": {"cipherString": "The career of a writer is comparable to that of a woman of easy virtue. You write first for pleasure, later for the pleasure of others and finally for money.", "encodeType": "random", "offset": 1, "shift": 1, "offset2": 1, "keyword": "", "keyword2": "", "alphabetSource": "ABCDEFGHIJKLMNOPQRSTUVWXYZ", "alphabetDest": "BYJUWSHTXZCFEOPQNADMKLRGVI", "curlang": "en", "replacement": {"A": "B", "B": "Y", "C": "J", "D": "U", "E": "W", "F": "S", "G": "H", "H": "T", "I": "X", "J": "Z", "K": "C", "L": "F", "M": "E", "N": "O", "O": "P", "P": "Q", "Q": "N", "R": "A", "S": "D", "T": "M", "U": "K", "V": "L", "W": "R", "X": "G", "Y": "V", "Z": "I"}, "editEntry": "2", "cipherType": "aristocrat", "question": "<p>Solve this aristocrat.</p>", "points": 250}, "CIPHER.4": {"cipherString": "Discipline is just doing the same thing the right way whether anyone's watching or not.", "encodeType": "random", "offset": 1, "shift": 1, "offset2": 1, "keyword": "", "keyword2": "", "alphabetSource": "ABCDEFGHIJKLMNOPQRSTUVWXYZ", "alphabetDest": "CAHQDKIREYNVTWPOGLMSZUFBXJ", "curlang": "en", "replacement": {"A": "C", "B": "A", "C": "H", "D": "Q", "E": "D", "F": "K", "G": "I", "H": "R", "I": "E", "J": "Y", "K": "N", "L": "V", "M": "T", "N": "W", "O": "P", "P": "O", "Q": "G", "R": "L", "S": "M", "T": "S", "U": "Z", "V": "U", "W": "F", "X": "B", "Y": "X", "Z": "J"}, "editEntry": "3", "cipherType": "aristocrat", "question": "<p>Solve this aristocrat.</p>", "points": 250}, "CIPHER.5": {"cipherString": "I was a big fan of Super Troopers, so working with the Broken Lizard guys was so much fun.", "encodeType": "random", "offset": 1, "shift": 1, "offset2": 1, "keyword": "", "keyword2": "", "alphabetSource": "ABCDEFGHIJKLMNOPQRSTUVWXYZ", "alphabetDest": "FKATRJDISLUMHVWZYXONQGBPCE", "curlang": "en", "replacement": {"A": "F", "B": "K", "C": "A", "D": "T", "E": "R", "F": "J", "G": "D", "H": "I", "I": "S", "J": "L", "K": "U", "L": "M", "M": "H", "N": "V", "O": "W", "P": "Z", "Q": "Y", "R": "X", "S": "O", "T": "N", "U": "Q", "V": "G", "W": "B", "X": "P", "Y": "C", "Z": "E"}, "editEntry": "4", "cipherType": "aristocrat", "question": "<p>Solve this aristocrat.</p>", "points": 250}, "CIPHER.6": {"cipherString": "When I was stalking my special lady friend on MySpace, people would always say, 'Is this really Marilyn Manson or some kind of psycho?' And I'm like, 'Both.'", "encodeType": "random", "offset": 1, "shift": 1, "offset2": 1, "keyword": "", "keyword2": "", "alphabetSource": "ABCDEFGHIJKLMNOPQRSTUVWXYZ", "alphabetDest": "VCLFANJQPBOXURMDZKYITGSWHE", "curlang": "en", "replacement": {"A": "V", "B": "C", "C": "L", "D": "F", "E": "A", "F": "N", "G": "J", "H": "Q", "I": "P", "J": "B", "K": "O", "L": "X", "M": "U", "N": "R", "O": "M", "P": "D", "Q": "Z", "R": "K", "S": "Y", "T": "I", "U": "T", "V": "G", "W": "S", "X": "W", "Y": "H", "Z": "E"}, "editEntry": "5", "cipherType": "aristocrat", "question": "<p>Solve this aristocrat.</p>", "points": 250}, "CIPHER.7": {"cipherString": "Never respect men merely for their riches, but rather for their philanthropy; we do not value the sun for its height, but for its use.", "encodeType": "random", "offset": 1, "shift": 1, "offset2": 1, "keyword": "", "keyword2": "", "alphabetSource": "ABCDEFGHIJKLMNOPQRSTUVWXYZ", "alphabetDest": "DWUFRIPNJOBQVHMASZLYTXGECK", "curlang": "en", "replacement": {"A": "D", "B": "W", "C": "U", "D": "F", "E": "R", "F": "I", "G": "P", "H": "N", "I": "J", "J": "O", "K": "B", "L": "Q", "M": "V", "N": "H", "O": "M", "P": "A", "Q": "S", "R": "Z", "S": "L", "T": "Y", "U": "T", "V": "X", "W": "G", "X": "E", "Y": "C", "Z": "K"}, "editEntry": "6", "cipherType": "aristocrat", "question": "<p>Solve this aristocrat.</p>", "points": 250}, "CIPHER.8": {"cipherString": "I can write a program that lets you break the copy protection on a music file. But I can't write a program that solders new connections onto a chip for you.", "encodeType": "random", "offset": 1, "shift": 1, "offset2": 1, "keyword": "", "keyword2": "", "alphabetSource": "ABCDEFGHIJKLMNOPQRSTUVWXYZ", "alphabetDest": "BCEJZXUYSQOFTANLVWHDKRGMIP", "curlang": "en", "replacement": {"A": "B", "B": "C", "C": "E", "D": "J", "E": "Z", "F": "X", "G": "U", "H": "Y", "I": "S", "J": "Q", "K": "O", "L": "F", "M": "T", "N": "A", "O": "N", "P": "L", "Q": "V", "R": "W", "S": "H", "T": "D", "U": "K", "V": "R", "W": "G", "X": "M", "Y": "I", "Z": "P"}, "editEntry": "7", "cipherType": "aristocrat", "question": "<p>Solve this aristocrat.</p>", "points": 250}, "CIPHER.9": {"cipherString": "It's quite highly possible that I have peaked. I mean, I just can't imagine what else I could do beyond this. It's really a bittersweet kind of feeling.", "encodeType": "random", "offset": 1, "shift": 1, "offset2": 1, "keyword": "", "keyword2": "", "alphabetSource": "ABCDEFGHIJKLMNOPQRSTUVWXYZ", "alphabetDest": "YEAMFCIBNKSWVZDXGUHQPLJORT", "curlang": "en", "replacement": {"A": "Y", "B": "E", "C": "A", "D": "M", "E": "F", "F": "C", "G": "I", "H": "B", "I": "N", "J": "K", "K": "S", "L": "W", "M": "V", "N": "Z", "O": "D", "P": "X", "Q": "G", "R": "U", "S": "H", "T": "Q", "U": "P", "V": "L", "W": "J", "X": "O", "Y": "R", "Z": "T"}, "editEntry": "8", "cipherType": "aristocrat", "question": "<p>Solve this aristocrat.</p>", "points": 250}, "CIPHER.10": {"cipherString": "Chronic Lyme causes arthritis, heart problems, stroke - even death.", "encodeType": "random", "offset": 1, "shift": 1, "offset2": 1, "keyword": "", "keyword2": "", "alphabetSource": "ABCDEFGHIJKLMNOPQRSTUVWXYZ", "alphabetDest": "HMKPBLTNUYGDACXIVQOFJWSZER", "curlang": "en", "replacement": {"A": "H", "B": "M", "C": "K", "D": "P", "E": "B", "F": "L", "G": "T", "H": "N", "I": "U", "J": "Y", "K": "G", "L": "D", "M": "A", "N": "C", "O": "X", "P": "I", "Q": "V", "R": "Q", "S": "O", "T": "F", "U": "J", "V": "W", "W": "S", "X": "Z", "Y": "E", "Z": "R"}, "editEntry": "9", "cipherType": "aristocrat", "question": "<p>Solve this aristocrat.</p>", "points": 250}, "CIPHER.11": {"cipherString": "Three grand essentials to happiness in this life are something to do, something to love, and something to hope for.", "encodeType": "random", "offset": 1, "shift": 1, "offset2": 1, "keyword": "", "keyword2": "", "alphabetSource": "ABCDEFGHIJKLMNOPQRSTUVWXYZ", "alphabetDest": "MCYJUEALGTXQZOSHRNVDBKFIWP", "curlang": "en", "replacement": {"A": "M", "B": "C", "C": "Y", "D": "J", "E": "U", "F": "E", "G": "A", "H": "L", "I": "G", "J": "T", "K": "X", "L": "Q", "M": "Z", "N": "O", "O": "S", "P": "H", "Q": "R", "R": "N", "S": "V", "T": "D", "U": "B", "V": "K", "W": "F", "X": "I", "Y": "W", "Z": "P"}, "editEntry": "10", "cipherType": "aristocrat", "question": "<p>Solve this aristocrat.</p>", "points": 250}, "CIPHER.12": {"cipherString": "New Orleans jazz is a complex and embracing art form that began about the same time as the blues and encompassed many of its excellences.", "encodeType": "random", "offset": 1, "shift": 1, "offset2": 1, "keyword": "", "keyword2": "", "alphabetSource": "ABCDEFGHIJKLMNOPQRSTUVWXYZ", "alphabetDest": "LSDFVZKBJHYTXMRIWCAUGONPEQ", "curlang": "en", "replacement": {"A": "L", "B": "S", "C": "D", "D": "F", "E": "V", "F": "Z", "G": "K", "H": "B", "I": "J", "J": "H", "K": "Y", "L": "T", "M": "X", "N": "M", "O": "R", "P": "I", "Q": "W", "R": "C", "S": "A", "T": "U", "U": "G", "V": "O", "W": "N", "X": "P", "Y": "E", "Z": "Q"}, "editEntry": "11", "cipherType": "aristocrat", "question": "<p>Solve this aristocrat.</p>", "points": 250}, "CIPHER.13": {"cipherString": "One of the tests of leadership is the ability to recognize a problem before it becomes an emergency.", "encodeType": "random", "offset": 1, "shift": 1, "offset2": 1, "keyword": "", "keyword2": "", "alphabetSource": "ABCDEFGHIJKLMNOPQRSTUVWXYZ", "alphabetDest": "POQWYUTZHXDIEKGAFJVSBNLCRM", "curlang": "en", "replacement": {"A": "P", "B": "O", "C": "Q", "D": "W", "E": "Y", "F": "U", "G": "T", "H": "Z", "I": "H", "J": "X", "K": "D", "L": "I", "M": "E", "N": "K", "O": "G", "P": "A", "Q": "F", "R": "J", "S": "V", "T": "S", "U": "B", "V": "N", "W": "L", "X": "C", "Y": "R", "Z": "M"}, "editEntry": "12", "cipherType": "aristocrat", "question": "<p>Solve this aristocrat.</p>", "points": 250}, "CIPHER.14": {"cipherString": "I think black Americans expect too much from individual black Americans in terms of changing the status quo.", "encodeType": "random", "offset": 1, "shift": 1, "offset2": 1, "keyword": "", "keyword2": "", "alphabetSource": "ABCDEFGHIJKLMNOPQRSTUVWXYZ", "alphabetDest": "YEMPHJOURXAGDKLTNZBCQWVFSI", "curlang": "en", "replacement": {"A": "Y", "B": "E", "C": "M", "D": "P", "E": "H", "F": "J", "G": "O", "H": "U", "I": "R", "J": "X", "K": "A", "L": "G", "M": "D", "N": "K", "O": "L", "P": "T", "Q": "N", "R": "Z", "S": "B", "T": "C", "U": "Q", "V": "W", "W": "V", "X": "F", "Y": "S", "Z": "I"}, "editEntry": "13", "cipherType": "aristocrat", "question": "<p>Solve this aristocrat.</p>", "points": 250}, "CIPHER.15": {"cipherString": "Get all the fools on your side and you can be elected to anything.", "encodeType": "random", "offset": 1, "shift": 1, "offset2": 1, "keyword": "", "keyword2": "", "alphabetSource": "ABCDEFGHIJKLMNOPQRSTUVWXYZ", "alphabetDest": "IKJAMXRCPDLGNOHWEQYZVTBSUF", "curlang": "en", "replacement": {"A": "I", "B": "K", "C": "J", "D": "A", "E": "M", "F": "X", "G": "R", "H": "C", "I": "P", "J": "D", "K": "L", "L": "G", "M": "N", "N": "O", "O": "H", "P": "W", "Q": "E", "R": "Q", "S": "Y", "T": "Z", "U": "V", "V": "T", "W": "B", "X": "S", "Y": "U", "Z": "F"}, "editEntry": "14", "cipherType": "aristocrat", "question": "<p>Solve this aristocrat.</p>", "points": 250}, "CIPHER.16": {"cipherString": "I fell in love with acting, just going to a lot of plays. My parents went to a lot of plays, and I went to a lot of schools that would get plays for kids.", "encodeType": "random", "offset": 1, "shift": 1, "offset2": 1, "keyword": "", "keyword2": "", "alphabetSource": "ABCDEFGHIJKLMNOPQRSTUVWXYZ", "alphabetDest": "XWNFHYOGSLPBZARUETMIKQJCDV", "curlang": "en", "replacement": {"A": "X", "B": "W", "C": "N", "D": "F", "E": "H", "F": "Y", "G": "O", "H": "G", "I": "S", "J": "L", "K": "P", "L": "B", "M": "Z", "N": "A", "O": "R", "P": "U", "Q": "E", "R": "T", "S": "M", "T": "I", "U": "K", "V": "Q", "W": "J", "X": "C", "Y": "D", "Z": "V"}, "editEntry": "15", "cipherType": "aristocrat", "question": "<p>Solve this aristocrat.</p>", "points": 250}, "CIPHER.17": {"cipherString": "You know you're getting old when you stoop to tie your shoelaces and wonder what else you could do while you're down there.", "encodeType": "random", "offset": 1, "shift": 1, "offset2": 1, "keyword": "", "keyword2": "", "alphabetSource": "ABCDEFGHIJKLMNOPQRSTUVWXYZ", "alphabetDest": "BLFMKYUOZSHNPTGDRWJIXQCAEV", "curlang": "en", "replacement": {"A": "B", "B": "L", "C": "F", "D": "M", "E": "K", "F": "Y", "G": "U", "H": "O", "I": "Z", "J": "S", "K": "H", "L": "N", "M": "P", "N": "T", "O": "G", "P": "D", "Q": "R", "R": "W", "S": "J", "T": "I", "U": "X", "V": "Q", "W": "C", "X": "A", "Y": "E", "Z": "V"}, "editEntry": "16", "cipherType": "aristocrat", "question": "<p>Solve this aristocrat.</p>", "points": 250}, "CIPHER.18": {"cipherString": "If you want total security, go to prison. There you're fed, clothed, given medical care and so on. The only thing lacking... is freedom.", "encodeType": "random", "offset": 1, "shift": 1, "offset2": 1, "keyword": "", "keyword2": "", "alphabetSource": "ABCDEFGHIJKLMNOPQRSTUVWXYZ", "alphabetDest": "CWMARYFXPGVJOUSNIELKHZDTQB", "curlang": "en", "replacement": {"A": "C", "B": "W", "C": "M", "D": "A", "E": "R", "F": "Y", "G": "F", "H": "X", "I": "P", "J": "G", "K": "V", "L": "J", "M": "O", "N": "U", "O": "S", "P": "N", "Q": "I", "R": "E", "S": "L", "T": "K", "U": "H", "V": "Z", "W": "D", "X": "T", "Y": "Q", "Z": "B"}, "editEntry": "17", "cipherType": "aristocrat", "question": "<p>Solve this aristocrat.</p>", "points": 250}, "CIPHER.19": {"cipherString": "Groups are grammatical fictions; only individuals exist, and each individual is different.", "encodeType": "random", "offset": 1, "shift": 1, "offset2": 1, "keyword": "", "keyword2": "", "alphabetSource": "ABCDEFGHIJKLMNOPQRSTUVWXYZ", "alphabetDest": "XVAGBELWCUNRFHIDMKQZYTSJOP", "curlang": "en", "replacement": {"A": "X", "B": "V", "C": "A", "D": "G", "E": "B", "F": "E", "G": "L", "H": "W", "I": "C", "J": "U", "K": "N", "L": "R", "M": "F", "N": "H", "O": "I", "P": "D", "Q": "M", "R": "K", "S": "Q", "T": "Z", "U": "Y", "V": "T", "W": "S", "X": "J", "Y": "O", "Z": "P"}, "editEntry": "18", "cipherType": "aristocrat", "question": "<p>Solve this aristocrat.</p>", "points": 250}, "CIPHER.20": {"cipherString": "These days, all we hear about is that the industry is in trouble. Everybody is so scared, but our mission statement is having no fear.", "encodeType": "random", "offset": 1, "shift": 1, "offset2": 1, "keyword": "", "keyword2": "", "alphabetSource": "ABCDEFGHIJKLMNOPQRSTUVWXYZ", "alphabetDest": "UPABMIDWJXFZYESLVTGOCRKNHQ", "curlang": "en", "replacement": {"A": "U", "B": "P", "C": "A", "D": "B", "E": "M", "F": "I", "G": "D", "H": "W", "I": "J", "J": "X", "K": "F", "L": "Z", "M": "Y", "N": "E", "O": "S", "P": "L", "Q": "V", "R": "T", "S": "G", "T": "O", "U": "C", "V": "R", "W": "K", "X": "N", "Y": "H", "Z": "Q"}, "editEntry": "19", "cipherType": "aristocrat", "question": "<p>Solve this aristocrat.</p>", "points": 250}, "CIPHER.21": {"cipherString": "Writing long hand is the last refuge. One needs the time it takes to put pencil to paper and let it run along the ruled line.", "encodeType": "random", "offset": 1, "shift": 1, "offset2": 1, "keyword": "", "keyword2": "", "alphabetSource": "ABCDEFGHIJKLMNOPQRSTUVWXYZ", "alphabetDest": "DQHUKMXTEYNBICAGOLJSWZFPVR", "curlang": "en", "replacement": {"A": "D", "B": "Q", "C": "H", "D": "U", "E": "K", "F": "M", "G": "X", "H": "T", "I": "E", "J": "Y", "K": "N", "L": "B", "M": "I", "N": "C", "O": "A", "P": "G", "Q": "O", "R": "L", "S": "J", "T": "S", "U": "W", "V": "Z", "W": "F", "X": "P", "Y": "V", "Z": "R"}, "editEntry": "20", "cipherType": "aristocrat", "question": "<p>Solve this aristocrat.</p>", "points": 250}, "CIPHER.22": {"cipherString": "But pleasures are like poppies spread, You seize the flow'r, its bloom is shed.", "encodeType": "random", "offset": 1, "shift": 1, "offset2": 1, "keyword": "", "keyword2": "", "alphabetSource": "ABCDEFGHIJKLMNOPQRSTUVWXYZ", "alphabetDest": "ILKGJRQOHACEPTNXWMBYFUSVZD", "curlang": "en", "replacement": {"A": "I", "B": "L", "C": "K", "D": "G", "E": "J", "F": "R", "G": "Q", "H": "O", "I": "H", "J": "A", "K": "C", "L": "E", "M": "P", "N": "T", "O": "N", "P": "X", "Q": "W", "R": "M", "S": "B", "T": "Y", "U": "F", "V": "U", "W": "S", "X": "V", "Y": "Z", "Z": "D"}, "editEntry": "21", "cipherType": "aristocrat", "question": "<p>Solve this aristocrat.</p>", "points": 250}, "CIPHER.23": {"cipherString": "I've loved thrillers and spy stories since I was a kid. It's probably not a bad rule of thumb to write the kinds of stories you love to read.", "encodeType": "random", "offset": 1, "shift": 1, "offset2": 1, "keyword": "", "keyword2": "", "alphabetSource": "ABCDEFGHIJKLMNOPQRSTUVWXYZ", "alphabetDest": "VENGZMQJRXAWBPKTDHIFSOYULC", "curlang": "en", "replacement": {"A": "V", "B": "E", "C": "N", "D": "G", "E": "Z", "F": "M", "G": "Q", "H": "J", "I": "R", "J": "X", "K": "A", "L": "W", "M": "B", "N": "P", "O": "K", "P": "T", "Q": "D", "R": "H", "S": "I", "T": "F", "U": "S", "V": "O", "W": "Y", "X": "U", "Y": "L", "Z": "C"}, "editEntry": "22", "cipherType": "aristocrat", "question": "<p>Solve this aristocrat.</p>", "points": 250}, "CIPHER.24": {"cipherString": "Once a month, try something you don't think you'd be good at. You can find such happy surprises.", "encodeType": "random", "offset": 1, "shift": 1, "offset2": 1, "keyword": "", "keyword2": "", "alphabetSource": "ABCDEFGHIJKLMNOPQRSTUVWXYZ", "alphabetDest": "MDGFYVLZAENKIHURBQXJCOPWST", "curlang": "en", "replacement": {"A": "M", "B": "D", "C": "G", "D": "F", "E": "Y", "F": "V", "G": "L", "H": "Z", "I": "A", "J": "E", "K": "N", "L": "K", "M": "I", "N": "H", "O": "U", "P": "R", "Q": "B", "R": "Q", "S": "X", "T": "J", "U": "C", "V": "O", "W": "P", "X": "W", "Y": "S", "Z": "T"}, "editEntry": "23", "cipherType": "aristocrat", "question": "<p>Solve this aristocrat.</p>", "points": 250}, "CIPHER.25": {"cipherString": "Nothing is so silly as the expression of a man who is being complimented.", "encodeType": "random", "offset": 1, "shift": 1, "offset2": 1, "keyword": "", "keyword2": "", "alphabetSource": "ABCDEFGHIJKLMNOPQRSTUVWXYZ", "alphabetDest": "YJUKHDVTSZIOREPWNLMBCGXFQA", "curlang": "en", "replacement": {"A": "Y", "B": "J", "C": "U", "D": "K", "E": "H", "F": "D", "G": "V", "H": "T", "I": "S", "J": "Z", "K": "I", "L": "O", "M": "R", "N": "E", "O": "P", "P": "W", "Q": "N", "R": "L", "S": "M", "T": "B", "U": "C", "V": "G", "W": "X", "X": "F", "Y": "Q", "Z": "A"}, "editEntry": "24", "cipherType": "aristocrat", "question": "<p>Solve this aristocrat.</p>", "points": 250}, "CIPHER.26": {"cipherString": "It was just us lampooning our own peer group, saying, well hey, where did this stuff come from? And where does British guys get to be so good at it suddenly?", "encodeType": "random", "offset": 1, "shift": 1, "offset2": 1, "keyword": "", "keyword2": "", "alphabetSource": "ABCDEFGHIJKLMNOPQRSTUVWXYZ", "alphabetDest": "TXVLYQKBGCRIPOMFWSAHENUZDJ", "curlang": "en", "replacement": {"A": "T", "B": "X", "C": "V", "D": "L", "E": "Y", "F": "Q", "G": "K", "H": "B", "I": "G", "J": "C", "K": "R", "L": "I", "M": "P", "N": "O", "O": "M", "P": "F", "Q": "W", "R": "S", "S": "A", "T": "H", "U": "E", "V": "N", "W": "U", "X": "Z", "Y": "D", "Z": "J"}, "editEntry": "25", "cipherType": "aristocrat", "question": "<p>Solve this aristocrat.</p>", "points": 250}, "CIPHER.27": {"cipherString": "Actors cannot choose the manner in which they are born. Consequently, it is the one gesture in their lives completely devoid of self-consciousness.", "encodeType": "random", "offset": 1, "shift": 1, "offset2": 1, "keyword": "", "keyword2": "", "alphabetSource": "ABCDEFGHIJKLMNOPQRSTUVWXYZ", "alphabetDest": "NXZFRJDSYQOGVUCWAHBPLMKEIT", "curlang": "en", "replacement": {"A": "N", "B": "X", "C": "Z", "D": "F", "E": "R", "F": "J", "G": "D", "H": "S", "I": "Y", "J": "Q", "K": "O", "L": "G", "M": "V", "N": "U", "O": "C", "P": "W", "Q": "A", "R": "H", "S": "B", "T": "P", "U": "L", "V": "M", "W": "K", "X": "E", "Y": "I", "Z": "T"}, "editEntry": "26", "cipherType": "aristocrat", "question": "<p>Solve this aristocrat.</p>", "points": 250}, "CIPHER.28": {"cipherString": "The old cathedrals are good, but the great blue dome that hangs over everything is better.", "encodeType": "random", "offset": 1, "shift": 1, "offset2": 1, "keyword": "", "keyword2": "", "alphabetSource": "ABCDEFGHIJKLMNOPQRSTUVWXYZ", "alphabetDest": "QSXHAVNKGWFOYBCLZPTRIUEDMJ", "curlang": "en", "replacement": {"A": "Q", "B": "S", "C": "X", "D": "H", "E": "A", "F": "V", "G": "N", "H": "K", "I": "G", "J": "W", "K": "F", "L": "O", "M": "Y", "N": "B", "O": "C", "P": "L", "Q": "Z", "R": "P", "S": "T", "T": "R", "U": "I", "V": "U", "W": "E", "X": "D", "Y": "M", "Z": "J"}, "editEntry": "27", "cipherType": "aristocrat", "question": "<p>Solve this aristocrat.</p>", "points": 250}, "CIPHER.29": {"cipherString": "We work in the dark - we do what we can - we give what we have. Our doubt is our passion and our passion is our task. The rest is the madness of art.", "encodeType": "random", "offset": 1, "shift": 1, "offset2": 1, "keyword": "", "keyword2": "", "alphabetSource": "ABCDEFGHIJKLMNOPQRSTUVWXYZ", "alphabetDest": "FTZMQRYVEUJPADWIHBCONSLKGX", "curlang": "en", "replacement": {"A": "F", "B": "T", "C": "Z", "D": "M", "E": "Q", "F": "R", "G": "Y", "H": "V", "I": "E", "J": "U", "K": "J", "L": "P", "M": "A", "N": "D", "O": "W", "P": "I", "Q": "H", "R": "B", "S": "C", "T": "O", "U": "N", "V": "S", "W": "L", "X": "K", "Y": "G", "Z": "X"}, "editEntry": "28", "cipherType": "aristocrat", "question": "<p>Solve this aristocrat.</p>", "points": 250}, "CIPHER.30": {"cipherString": "It's a constant battle for everybody, but you need to be happy with yourself.", "encodeType": "random", "offset": 1, "shift": 1, "offset2": 1, "keyword": "", "keyword2": "", "alphabetSource": "ABCDEFGHIJKLMNOPQRSTUVWXYZ", "alphabetDest": "YWJINMVDZFXGEOLHRSQUPKTABC", "curlang": "en", "replacement": {"A": "Y", "B": "W", "C": "J", "D": "I", "E": "N", "F": "M", "G": "V", "H": "D", "I": "Z", "J": "F", "K": "X", "L": "G", "M": "E", "N": "O", "O": "L", "P": "H", "Q": "R", "R": "S", "S": "Q", "T": "U", "U": "P", "V": "K", "W": "T", "X": "A", "Y": "B", "Z": "C"}, "editEntry": "29", "cipherType": "aristocrat", "question": "<p>Solve this aristocrat.</p>", "points": 250}, "CIPHER.31": {"cipherString": "Be careful the environment you choose for it will shape you; be careful the friends you choose for you will become like them.", "encodeType": "random", "offset": 1, "shift": 1, "offset2": 1, "keyword": "", "keyword2": "", "alphabetSource": "ABCDEFGHIJKLMNOPQRSTUVWXYZ", "alphabetDest": "LJIOBWTFVYPGCXQRSMZAKNEHUD", "curlang": "en", "replacement": {"A": "L", "B": "J", "C": "I", "D": "O", "E": "B", "F": "W", "G": "T", "H": "F", "I": "V", "J": "Y", "K": "P", "L": "G", "M": "C", "N": "X", "O": "Q", "P": "R", "Q": "S", "R": "M", "S": "Z", "T": "A", "U": "K", "V": "N", "W": "E", "X": "H", "Y": "U", "Z": "D"}, "editEntry": "30", "cipherType": "aristocrat", "question": "<p>Solve this aristocrat.</p>", "points": 250}, "CIPHER.32": {"cipherString": "I listen to the audience and try and bounce with them. All audiences are different. But they are all homo sapiens.", "encodeType": "random", "offset": 1, "shift": 1, "offset2": 1, "keyword": "", "keyword2": "", "alphabetSource": "ABCDEFGHIJKLMNOPQRSTUVWXYZ", "alphabetDest": "FDPSTKIBHRANXWVUGJOYLZEQCM", "curlang": "en", "replacement": {"A": "F", "B": "D", "C": "P", "D": "S", "E": "T", "F": "K", "G": "I", "H": "B", "I": "H", "J": "R", "K": "A", "L": "N", "M": "X", "N": "W", "O": "V", "P": "U", "Q": "G", "R": "J", "S": "O", "T": "Y", "U": "L", "V": "Z", "W": "E", "X": "Q", "Y": "C", "Z": "M"}, "editEntry": "31", "cipherType": "aristocrat", "question": "<p>Solve this aristocrat.</p>", "points": 250}, "CIPHER.33": {"cipherString": "Being the richest man in the cemetery doesn't matter to me. Going to bed at night saying we've done something wonderful, that's what matters to me.", "encodeType": "random", "offset": 1, "shift": 1, "offset2": 1, "keyword": "", "keyword2": "", "alphabetSource": "ABCDEFGHIJKLMNOPQRSTUVWXYZ", "alphabetDest": "BUTVDHJEMCZKLAYWNOPIXGSFRQ", "curlang": "en", "replacement": {"A": "B", "B": "U", "C": "T", "D": "V", "E": "D", "F": "H", "G": "J", "H": "E", "I": "M", "J": "C", "K": "Z", "L": "K", "M": "L", "N": "A", "O": "Y", "P": "W", "Q": "N", "R": "O", "S": "P", "T": "I", "U": "X", "V": "G", "W": "S", "X": "F", "Y": "R", "Z": "Q"}, "editEntry": "32", "cipherType": "aristocrat", "question": "<p>Solve this aristocrat.</p>", "points": 250}, "CIPHER.34": {"cipherString": "I never thought in a million years that I would do a weekly series.", "encodeType": "random", "offset": 1, "shift": 1, "offset2": 1, "keyword": "", "keyword2": "", "alphabetSource": "ABCDEFGHIJKLMNOPQRSTUVWXYZ", "alphabetDest": "ZOXRIWKFPVMSQLNDEACYTBUJHG", "curlang": "en", "replacement": {"A": "Z", "B": "O", "C": "X", "D": "R", "E": "I", "F": "W", "G": "K", "H": "F", "I": "P", "J": "V", "K": "M", "L": "S", "M": "Q", "N": "L", "O": "N", "P": "D", "Q": "E", "R": "A", "S": "C", "T": "Y", "U": "T", "V": "B", "W": "U", "X": "J", "Y": "H", "Z": "G"}, "editEntry": "33", "cipherType": "aristocrat", "question": "<p>Solve this aristocrat.</p>", "points": 250}, "CIPHER.35": {"cipherString": "Nothing except a battle lost can be half so melancholy as a battle won.", "encodeType": "random", "offset": 1, "shift": 1, "offset2": 1, "keyword": "", "keyword2": "", "alphabetSource": "ABCDEFGHIJKLMNOPQRSTUVWXYZ", "alphabetDest": "GCEINTHRUQSWXLKVFJOZYAMPDB", "curlang": "en", "replacement": {"A": "G", "B": "C", "C": "E", "D": "I", "E": "N", "F": "T", "G": "H", "H": "R", "I": "U", "J": "Q", "K": "S", "L": "W", "M": "X", "N": "L", "O": "K", "P": "V", "Q": "F", "R": "J", "S": "O", "T": "Z", "U": "Y", "V": "A", "W": "M", "X": "P", "Y": "D", "Z": "B"}, "editEntry": "34", "cipherType": "aristocrat", "question": "<p>Solve this aristocrat.</p>", "points": 250}, "CIPHER.36": {"cipherString": "If you live to be 1000 years old, I hope I live to be 1000 minus 1 day, so I never have to live without you.", "encodeType": "random", "offset": 1, "shift": 1, "offset2": 1, "keyword": "", "keyword2": "", "alphabetSource": "ABCDEFGHIJKLMNOPQRSTUVWXYZ", "alphabetDest": "JGVYSCTRMLXWZBUQHKAFEODNIP", "curlang": "en", "replacement": {"A": "J", "B": "G", "C": "V", "D": "Y", "E": "S", "F": "C", "G": "T", "H": "R", "I": "M", "J": "L", "K": "X", "L": "W", "M": "Z", "N": "B", "O": "U", "P": "Q", "Q": "H", "R": "K", "S": "A", "T": "F", "U": "E", "V": "O", "W": "D", "X": "N", "Y": "I", "Z": "P"}, "editEntry": "35", "cipherType": "aristocrat", "question": "<p>Solve this aristocrat.</p>", "points": 250}, "CIPHER.37": {"cipherString": "In science, the credit goes to the man who convinces the world, not to whom the idea first occurs.", "encodeType": "random", "offset": 1, "shift": 1, "offset2": 1, "keyword": "", "keyword2": "", "alphabetSource": "ABCDEFGHIJKLMNOPQRSTUVWXYZ", "alphabetDest": "QWJRIYBZXALNSDMTOUKVCHEGPF", "curlang": "en", "replacement": {"A": "Q", "B": "W", "C": "J", "D": "R", "E": "I", "F": "Y", "G": "B", "H": "Z", "I": "X", "J": "A", "K": "L", "L": "N", "M": "S", "N": "D", "O": "M", "P": "T", "Q": "O", "R": "U", "S": "K", "T": "V", "U": "C", "V": "H", "W": "E", "X": "G", "Y": "P", "Z": "F"}, "editEntry": "36", "cipherType": "aristocrat", "question": "<p>Solve this aristocrat.</p>", "points": 250}, "CIPHER.38": {"cipherString": "The interpretation of dreams is the royal road to a knowledge of the unconscious activities of the mind.", "encodeType": "random", "offset": 1, "shift": 1, "offset2": 1, "keyword": "", "keyword2": "", "alphabetSource": "ABCDEFGHIJKLMNOPQRSTUVWXYZ", "alphabetDest": "QWOFRGELMHCUPINVTBZJXYDSKA", "curlang": "en", "replacement": {"A": "Q", "B": "W", "C": "O", "D": "F", "E": "R", "F": "G", "G": "E", "H": "L", "I": "M", "J": "H", "K": "C", "L": "U", "M": "P", "N": "I", "O": "N", "P": "V", "Q": "T", "R": "B", "S": "Z", "T": "J", "U": "X", "V": "Y", "W": "D", "X": "S", "Y": "K", "Z": "A"}, "editEntry": "37", "cipherType": "aristocrat", "question": "<p>Solve this aristocrat.</p>", "points": 250}, "CIPHER.39": {"cipherString": "We don't really need reviewers, just first-night reporters who will tell us faithfully whether or not the audience liked the show.", "encodeType": "random", "offset": 1, "shift": 1, "offset2": 1, "keyword": "", "keyword2": "", "alphabetSource": "ABCDEFGHIJKLMNOPQRSTUVWXYZ", "alphabetDest": "FPWEKMSUJDCZYHXVTANBGRQIOL", "curlang": "en", "replacement": {"A": "F", "B": "P", "C": "W", "D": "E", "E": "K", "F": "M", "G": "S", "H": "U", "I": "J", "J": "D", "K": "C", "L": "Z", "M": "Y", "N": "H", "O": "X", "P": "V", "Q": "T", "R": "A", "S": "N", "T": "B", "U": "G", "V": "R", "W": "Q", "X": "I", "Y": "O", "Z": "L"}, "editEntry": "38", "cipherType": "aristocrat", "question": "<p>Solve this aristocrat.</p>", "points": 250}, "CIPHER.40": {"cipherString": "I've had journalists beg me to please say something negative about my estate.", "encodeType": "random", "offset": 1, "shift": 1, "offset2": 1, "keyword": "", "keyword2": "", "alphabetSource": "ABCDEFGHIJKLMNOPQRSTUVWXYZ", "alphabetDest": "XVWIOUJTHBPQFZNYGECKSLDRAM", "curlang": "en", "replacement": {"A": "X", "B": "V", "C": "W", "D": "I", "E": "O", "F": "U", "G": "J", "H": "T", "I": "H", "J": "B", "K": "P", "L": "Q", "M": "F", "N": "Z", "O": "N", "P": "Y", "Q": "G", "R": "E", "S": "C", "T": "K", "U": "S", "V": "L", "W": "D", "X": "R", "Y": "A", "Z": "M"}, "editEntry": "39", "cipherType": "aristocrat", "question": "<p>Solve this aristocrat.</p>", "points": 250}, "CIPHER.41": {"cipherString": "A difference of taste in jokes is a great strain on the affections.", "encodeType": "random", "offset": 1, "shift": 1, "offset2": 1, "keyword": "", "keyword2": "", "alphabetSource": "ABCDEFGHIJKLMNOPQRSTUVWXYZ", "alphabetDest": "CKOAZWJSXLPNRMFDBGYIEUHVTQ", "curlang": "en", "replacement": {"A": "C", "B": "K", "C": "O", "D": "A", "E": "Z", "F": "W", "G": "J", "H": "S", "I": "X", "J": "L", "K": "P", "L": "N", "M": "R", "N": "M", "O": "F", "P": "D", "Q": "B", "R": "G", "S": "Y", "T": "I", "U": "E", "V": "U", "W": "H", "X": "V", "Y": "T", "Z": "Q"}, "editEntry": "40", "cipherType": "aristocrat", "question": "<p>Solve this aristocrat.</p>", "points": 250}, "CIPHER.42": {"cipherString": "We know from science that nothing in the universe exists as an isolated or independent entity.", "encodeType": "random", "offset": 1, "shift": 1, "offset2": 1, "keyword": "", "keyword2": "", "alphabetSource": "ABCDEFGHIJKLMNOPQRSTUVWXYZ", "alphabetDest": "SERVMLIWHOQZJYPUAGTKXNFBCD", "curlang": "en", "replacement": {"A": "S", "B": "E", "C": "R", "D": "V", "E": "M", "F": "L", "G": "I", "H": "W", "I": "H", "J": "O", "K": "Q", "L": "Z", "M": "J", "N": "Y", "O": "P", "P": "U", "Q": "A", "R": "G", "S": "T", "T": "K", "U": "X", "V": "N", "W": "F", "X": "B", "Y": "C", "Z": "D"}, "editEntry": "41", "cipherType": "aristocrat", "question": "<p>Solve this aristocrat.</p>", "points": 250}, "CIPHER.43": {"cipherString": "Leadership is about doing what you know is right - even when a growing din of voices around you is trying to convince you to accept what you know to be wrong.", "encodeType": "random", "offset": 1, "shift": 1, "offset2": 1, "keyword": "", "keyword2": "", "alphabetSource": "ABCDEFGHIJKLMNOPQRSTUVWXYZ", "alphabetDest": "GIQSWXFMRVUTOHYNJAZDLEBCKP", "curlang": "en", "replacement": {"A": "G", "B": "I", "C": "Q", "D": "S", "E": "W", "F": "X", "G": "F", "H": "M", "I": "R", "J": "V", "K": "U", "L": "T", "M": "O", "N": "H", "O": "Y", "P": "N", "Q": "J", "R": "A", "S": "Z", "T": "D", "U": "L", "V": "E", "W": "B", "X": "C", "Y": "K", "Z": "P"}, "editEntry": "42", "cipherType": "aristocrat", "question": "<p>Solve this aristocrat.</p>", "points": 250}, "CIPHER.44": {"cipherString": "I'd like to help other kids with dyslexia, because I'm dyslexic. It was very hard, and I know that what I went through, other kids are going through.", "encodeType": "random", "offset": 1, "shift": 1, "offset2": 1, "keyword": "", "keyword2": "", "alphabetSource": "ABCDEFGHIJKLMNOPQRSTUVWXYZ", "alphabetDest": "MYWXDQUSRAPBOCZILETNKJGHFV", "curlang": "en", "replacement": {"A": "M", "B": "Y", "C": "W", "D": "X", "E": "D", "F": "Q", "G": "U", "H": "S", "I": "R", "J": "A", "K": "P", "L": "B", "M": "O", "N": "C", "O": "Z", "P": "I", "Q": "L", "R": "E", "S": "T", "T": "N", "U": "K", "V": "J", "W": "G", "X": "H", "Y": "F", "Z": "V"}, "editEntry": "43", "cipherType": "aristocrat", "question": "<p>Solve this aristocrat.</p>", "points": 250}, "CIPHER.45": {"cipherString": "Men always want to be a woman's first love - women like to be a man's last romance.", "encodeType": "random", "offset": 1, "shift": 1, "offset2": 1, "keyword": "", "keyword2": "", "alphabetSource": "ABCDEFGHIJKLMNOPQRSTUVWXYZ", "alphabetDest": "HAPYFDNTOCMJVEQXBSKUIZGWLR", "curlang": "en", "replacement": {"A": "H", "B": "A", "C": "P", "D": "Y", "E": "F", "F": "D", "G": "N", "H": "T", "I": "O", "J": "C", "K": "M", "L": "J", "M": "V", "N": "E", "O": "Q", "P": "X", "Q": "B", "R": "S", "S": "K", "T": "U", "U": "I", "V": "Z", "W": "G", "X": "W", "Y": "L", "Z": "R"}, "editEntry": "44", "cipherType": "aristocrat", "question": "<p>Solve this aristocrat.</p>", "points": 250}, "CIPHER.46": {"cipherString": "Originality does not consist in saying what no one has ever said before, but in saying exactly what you think yourself.", "encodeType": "random", "offset": 1, "shift": 1, "offset2": 1, "keyword": "", "keyword2": "", "alphabetSource": "ABCDEFGHIJKLMNOPQRSTUVWXYZ", "alphabetDest": "LSFPCKRWNZITDJMQYAHXBGUEVO", "curlang": "en", "replacement": {"A": "L", "B": "S", "C": "F", "D": "P", "E": "C", "F": "K", "G": "R", "H": "W", "I": "N", "J": "Z", "K": "I", "L": "T", "M": "D", "N": "J", "O": "M", "P": "Q", "Q": "Y", "R": "A", "S": "H", "T": "X", "U": "B", "V": "G", "W": "U", "X": "E", "Y": "V", "Z": "O"}, "editEntry": "45", "cipherType": "aristocrat", "question": "<p>Solve this aristocrat.</p>", "points": 250}, "CIPHER.47": {"cipherString": "If your Riches are yours, why don't you take them with you to t'other World?", "encodeType": "random", "offset": 1, "shift": 1, "offset2": 1, "keyword": "", "keyword2": "", "alphabetSource": "ABCDEFGHIJKLMNOPQRSTUVWXYZ", "alphabetDest": "WLYIGUHODAJFSVMXZEBNKCQRPT", "curlang": "en", "replacement": {"A": "W", "B": "L", "C": "Y", "D": "I", "E": "G", "F": "U", "G": "H", "H": "O", "I": "D", "J": "A", "K": "J", "L": "F", "M": "S", "N": "V", "O": "M", "P": "X", "Q": "Z", "R": "E", "S": "B", "T": "N", "U": "K", "V": "C", "W": "Q", "X": "R", "Y": "P", "Z": "T"}, "editEntry": "46", "cipherType": "aristocrat", "question": "<p>Solve this aristocrat.</p>", "points": 250}, "CIPHER.48": {"cipherString": "Maturity - among other things, the unclouded happiness of the child at play, who takes it for granted that he is at one with his play-mates.", "encodeType": "random", "offset": 1, "shift": 1, "offset2": 1, "keyword": "", "keyword2": "", "alphabetSource": "ABCDEFGHIJKLMNOPQRSTUVWXYZ", "alphabetDest": "WIOVXGMKCDRHUPTZBAJSQLYNEF", "curlang": "en", "replacement": {"A": "W", "B": "I", "C": "O", "D": "V", "E": "X", "F": "G", "G": "M", "H": "K", "I": "C", "J": "D", "K": "R", "L": "H", "M": "U", "N": "P", "O": "T", "P": "Z", "Q": "B", "R": "A", "S": "J", "T": "S", "U": "Q", "V": "L", "W": "Y", "X": "N", "Y": "E", "Z": "F"}, "editEntry": "47", "cipherType": "aristocrat", "question": "<p>Solve this aristocrat.</p>", "points": 250}, "CIPHER.49": {"cipherString": "As far as my favorite sites, I do a lot of mundane stuff on line because I travel so much.", "encodeType": "random", "offset": 1, "shift": 1, "offset2": 1, "keyword": "", "keyword2": "", "alphabetSource": "ABCDEFGHIJKLMNOPQRSTUVWXYZ", "alphabetDest": "IZHXBAUOKRDVYEWFNCPMQSJTGL", "curlang": "en", "replacement": {"A": "I", "B": "Z", "C": "H", "D": "X", "E": "B", "F": "A", "G": "U", "H": "O", "I": "K", "J": "R", "K": "D", "L": "V", "M": "Y", "N": "E", "O": "W", "P": "F", "Q": "N", "R": "C", "S": "P", "T": "M", "U": "Q", "V": "S", "W": "J", "X": "T", "Y": "G", "Z": "L"}, "editEntry": "48", "cipherType": "aristocrat", "question": "<p>Solve this aristocrat.</p>", "points": 250}, "CIPHER.50": {"cipherString": "There was a Republican majority of the Senate, and it tempered the nature of the nominations being made.", "encodeType": "random", "offset": 1, "shift": 1, "offset2": 1, "keyword": "", "keyword2": "", "alphabetSource": "ABCDEFGHIJKLMNOPQRSTUVWXYZ", "alphabetDest": "KWSLPAYJRXFVNBZUECTOGIDMHQ", "curlang": "en", "replacement": {"A": "K", "B": "W", "C": "S", "D": "L", "E": "P", "F": "A", "G": "Y", "H": "J", "I": "R", "J": "X", "K": "F", "L": "V", "M": "N", "N": "B", "O": "Z", "P": "U", "Q": "E", "R": "C", "S": "T", "T": "O", "U": "G", "V": "I", "W": "D", "X": "M", "Y": "H", "Z": "Q"}, "editEntry": "49", "cipherType": "aristocrat", "question": "<p>Solve this aristocrat.</p>", "points": 250}}