{"TEST.0": {"timed": 0, "count": 5, "questions": [1, 2, 3, 4, 5], "title": "l", "useCustomHeader": false, "customHeader": "", "testtype": "cstate"}, "CIPHER.0": {"cipherString": "My experience as a young actor on network television was that I couldn't make it work. I was drowning as an actor.", "encodeType": "random", "offset": 1, "shift": 1, "offset2": 1, "keyword": "", "keyword2": "", "alphabetSource": "ABCDEFGHIJKLMNOPQRSTUVWXYZ", "alphabetDest": "PJYXDCQGZSHOLBERIWVUNAMKTF", "curlang": "en", "replacement": {"A": "P", "B": "J", "C": "Y", "D": "X", "E": "D", "F": "C", "G": "Q", "H": "G", "I": "Z", "J": "S", "K": "H", "L": "O", "M": "L", "N": "B", "O": "E", "P": "R", "Q": "I", "R": "W", "S": "V", "T": "U", "U": "N", "V": "A", "W": "M", "X": "K", "Y": "T", "Z": "F"}, "editEntry": "0", "cipherType": "aristocrat", "question": "<p>Solve this aristocrat.</p>", "points": 250}, "CIPHER.1": {"cipherString": "If we have no peace, it is because we have forgotten that we belong to each other.", "encodeType": "random", "offset": 1, "shift": 1, "offset2": 1, "keyword": "", "keyword2": "", "alphabetSource": "ABCDEFGHIJKLMNOPQRSTUVWXYZ", "alphabetDest": "HCTBUYJMVXNESFRWKOQIPLADZG", "curlang": "en", "replacement": {"A": "H", "B": "C", "C": "T", "D": "B", "E": "U", "F": "Y", "G": "J", "H": "M", "I": "V", "J": "X", "K": "N", "L": "E", "M": "S", "N": "F", "O": "R", "P": "W", "Q": "K", "R": "O", "S": "Q", "T": "I", "U": "P", "V": "L", "W": "A", "X": "D", "Y": "Z", "Z": "G"}, "editEntry": "0", "cipherType": "aristocrat", "question": "<p>Solve this aristocrat.</p>", "points": 250}, "CIPHER.2": {"cipherString": "Occupy yourself in beholding and bewailing your own imperfections rather than contemplating the imperfections of others.", "encodeType": "random", "offset": 1, "shift": 1, "offset2": 1, "keyword": "", "keyword2": "", "alphabetSource": "ABCDEFGHIJKLMNOPQRSTUVWXYZ", "alphabetDest": "NROYWJZEDVTAQXSGLBHCKPIUMF", "curlang": "en", "replacement": {"A": "N", "B": "R", "C": "O", "D": "Y", "E": "W", "F": "J", "G": "Z", "H": "E", "I": "D", "J": "V", "K": "T", "L": "A", "M": "Q", "N": "X", "O": "S", "P": "G", "Q": "L", "R": "B", "S": "H", "T": "C", "U": "K", "V": "P", "W": "I", "X": "U", "Y": "M", "Z": "F"}, "editEntry": "1", "cipherType": "aristocrat", "question": "<p>Solve this aristocrat.</p>", "points": 250}, "CIPHER.3": {"cipherString": "Women do feel like they're in a box. Society, Hollywood, some men-they want to wrap women up in a neat little package.", "encodeType": "random", "offset": 1, "shift": 1, "offset2": 1, "keyword": "", "keyword2": "", "alphabetSource": "ABCDEFGHIJKLMNOPQRSTUVWXYZ", "alphabetDest": "JLFSWMCYVTZPBADQGNHXIUKERO", "curlang": "en", "replacement": {"A": "J", "B": "L", "C": "F", "D": "S", "E": "W", "F": "M", "G": "C", "H": "Y", "I": "V", "J": "T", "K": "Z", "L": "P", "M": "B", "N": "A", "O": "D", "P": "Q", "Q": "G", "R": "N", "S": "H", "T": "X", "U": "I", "V": "U", "W": "K", "X": "E", "Y": "R", "Z": "O"}, "editEntry": "2", "cipherType": "aristocrat", "question": "<p>Solve this aristocrat.</p>", "points": 250}, "CIPHER.4": {"cipherString": "No one will ever win the battle of the sexes; there's too much fraternizing with the enemy.", "encodeType": "random", "offset": 1, "shift": 1, "offset2": 1, "keyword": "", "keyword2": "", "alphabetSource": "ABCDEFGHIJKLMNOPQRSTUVWXYZ", "alphabetDest": "TIGAZCFMYPBEWSHJNOVLDXUKQR", "curlang": "en", "replacement": {"A": "T", "B": "I", "C": "G", "D": "A", "E": "Z", "F": "C", "G": "F", "H": "M", "I": "Y", "J": "P", "K": "B", "L": "E", "M": "W", "N": "S", "O": "H", "P": "J", "Q": "N", "R": "O", "S": "V", "T": "L", "U": "D", "V": "X", "W": "U", "X": "K", "Y": "Q", "Z": "R"}, "editEntry": "3", "cipherType": "aristocrat", "question": "<p>Solve this aristocrat.</p>", "points": 250}, "CIPHER.5": {"cipherString": "A woman knows by intuition, or instinct, what is best for herself.", "encodeType": "random", "offset": 1, "shift": 1, "offset2": 1, "keyword": "", "keyword2": "", "alphabetSource": "ABCDEFGHIJKLMNOPQRSTUVWXYZ", "alphabetDest": "MIXUNYAZFWGRLOCSDBVJTKEHQP", "curlang": "en", "replacement": {"A": "M", "B": "I", "C": "X", "D": "U", "E": "N", "F": "Y", "G": "A", "H": "Z", "I": "F", "J": "W", "K": "G", "L": "R", "M": "L", "N": "O", "O": "C", "P": "S", "Q": "D", "R": "B", "S": "V", "T": "J", "U": "T", "V": "K", "W": "E", "X": "H", "Y": "Q", "Z": "P"}, "editEntry": "4", "cipherType": "aristocrat", "question": "<p>Solve this aristocrat.</p>", "points": 250}}