{"TEST.0": {"timed": 0, "count": 10, "questions": [1, 2, 3, 4, 5, 6, 7, 8, 9, 10], "title": "MorbitPractice", "useCustomHeader": false, "customHeader": "", "testtype": "cstate"}, "CIPHER.0": {"cipherString": "I describe my works as books, but my publishers in Spain, in the United States, and elsewhere insist on calling them novels.", "encodeType": "random", "offset": 1, "shift": 1, "offset2": 1, "keyword": "", "keyword2": "", "alphabetSource": "ABCDEFGHIJKLMNOPQRSTUVWXYZ", "alphabetDest": "FPZKGIUMSAVTNJYHXEOWQBCDLR", "curlang": "en", "replacement": {"A": "F", "B": "P", "C": "Z", "D": "K", "E": "G", "F": "I", "G": "U", "H": "M", "I": "S", "J": "A", "K": "V", "L": "T", "M": "N", "N": "J", "O": "Y", "P": "H", "Q": "X", "R": "E", "S": "O", "T": "W", "U": "Q", "V": "B", "W": "C", "X": "D", "Y": "L", "Z": "R"}, "editEntry": "0", "cipherType": "aristocrat", "question": "<p>Solve this aristocrat.</p>", "points": 250}, "CIPHER.1": {"cipherString": "Just by luck, I picked good heroes to worship.", "cipherType": "morbit", "curlang": "en", "editEntry": "0", "offset": null, "alphabetSource": "", "alphabetDest": "", "shift": null, "offset2": null, "replacement": {"OO": "7", "O-": "2", "OX": "3", "-O": "8", "--": "4", "-X": "6", "XO": "5", "X-": "9", "XX": "1"}, "operation": "decode", "points": 225, "question": "<p>Decode this quote which has been encoded using the Morbit cipher. OO,OX,X-,XO,XX matches to 7,3,9,5,1.</p>", "hint": "123456"}, "CIPHER.2": {"cipherString": "Love without conversation is impossible.", "cipherType": "morbit", "curlang": "en", "editEntry": "1", "offset": null, "alphabetSource": "", "alphabetDest": "", "shift": null, "offset2": null, "replacement": {"OO": "9", "O-": "2", "OX": "4", "-O": "6", "--": "3", "-X": "7", "XO": "5", "X-": "8", "XX": "1"}, "operation": "decode", "points": 225, "question": "<p>Decode this quote which has been encoded using the Morbit cipher. OO,OX,X-,XO,XX matches to 9,4,8,5,1.</p>", "hint": "123456"}, "CIPHER.3": {"cipherString": "It is certain because it is impossible.", "cipherType": "morbit", "curlang": "en", "editEntry": "2", "offset": null, "alphabetSource": "", "alphabetDest": "", "shift": null, "offset2": null, "replacement": {"OO": "3", "O-": "6", "OX": "1", "-O": "2", "--": "4", "-X": "5", "XO": "7", "X-": "8", "XX": "9"}, "operation": "decode", "points": 225, "question": "<p>Decode this quote which has been encoded using the Morbit cipher. OO,OX,X-,XO,XX matches to 3,1,8,7,9.</p>", "hint": "123456"}, "CIPHER.4": {"cipherString": "Concrete is, essentially, the color of bad weather.", "cipherType": "morbit", "curlang": "en", "editEntry": "3", "offset": null, "alphabetSource": "", "alphabetDest": "", "shift": null, "offset2": null, "replacement": {"OO": "9", "O-": "7", "OX": "2", "-O": "4", "--": "8", "-X": "1", "XO": "3", "X-": "5", "XX": "6"}, "operation": "decode", "points": 225, "question": "<p>Decode this quote which has been encoded using the Morbit cipher. OO,OX,X-,XO,XX matches to 9,2,5,3,6.</p>", "hint": "123456"}, "CIPHER.5": {"cipherString": "My reputation grows with every failure.", "cipherType": "morbit", "curlang": "en", "editEntry": "4", "offset": null, "alphabetSource": "", "alphabetDest": "", "shift": null, "offset2": null, "replacement": {"OO": "3", "O-": "6", "OX": "1", "-O": "5", "--": "2", "-X": "9", "XO": "8", "X-": "4", "XX": "7"}, "operation": "decode", "points": 225, "question": "<p>Decode this quote which has been encoded using the Morbit cipher. OO,OX,X-,XO,XX matches to 3,1,4,8,7.</p>", "hint": "123456"}, "CIPHER.6": {"cipherString": "There is no success without hardship.", "cipherType": "morbit", "curlang": "en", "editEntry": "5", "offset": null, "alphabetSource": "", "alphabetDest": "", "shift": null, "offset2": null, "replacement": {"OO": "7", "O-": "8", "OX": "6", "-O": "3", "--": "9", "-X": "4", "XO": "2", "X-": "1", "XX": "5"}, "operation": "decode", "points": 225, "question": "<p>Decode this quote which has been encoded using the Morbit cipher. OO,OX,X-,XO,XX matches to 7,6,1,2,5.</p>", "hint": "123456"}, "CIPHER.7": {"cipherString": "Being a barber is about taking care of the people.", "cipherType": "morbit", "curlang": "en", "editEntry": "6", "offset": null, "alphabetSource": "", "alphabetDest": "", "shift": null, "offset2": null, "replacement": {"OO": "8", "O-": "3", "OX": "2", "-O": "5", "--": "7", "-X": "9", "XO": "1", "X-": "4", "XX": "6"}, "operation": "decode", "points": 225, "question": "<p>Decode this quote which has been encoded using the Morbit cipher. OO,OX,X-,XO,XX matches to 8,2,4,1,6.</p>", "hint": "123456"}, "CIPHER.8": {"cipherString": "People judge you by the way you play in the playoffs.", "cipherType": "morbit", "curlang": "en", "editEntry": "7", "offset": null, "alphabetSource": "", "alphabetDest": "", "shift": null, "offset2": null, "replacement": {"OO": "8", "O-": "5", "OX": "1", "-O": "4", "--": "2", "-X": "7", "XO": "6", "X-": "9", "XX": "3"}, "operation": "decode", "points": 225, "question": "<p>Decode this quote which has been encoded using the Morbit cipher. OO,OX,X-,XO,XX matches to 8,1,9,6,3.</p>", "hint": "123456"}, "CIPHER.9": {"cipherString": "The way is not in the sky. The way is in the heart.", "cipherType": "morbit", "curlang": "en", "editEntry": "8", "offset": null, "alphabetSource": "", "alphabetDest": "", "shift": null, "offset2": null, "replacement": {"OO": "3", "O-": "5", "OX": "9", "-O": "2", "--": "1", "-X": "8", "XO": "7", "X-": "6", "XX": "4"}, "operation": "decode", "points": 225, "question": "<p>Decode this quote which has been encoded using the Morbit cipher. OO,OX,X-,XO,XX matches to 3,9,6,7,4.</p>", "hint": "123456"}, "CIPHER.10": {"cipherString": "I was on a train of lies. I couldn't jump off.", "cipherType": "morbit", "curlang": "en", "editEntry": "9", "offset": null, "alphabetSource": "", "alphabetDest": "", "shift": null, "offset2": null, "replacement": {"OO": "4", "O-": "7", "OX": "9", "-O": "6", "--": "8", "-X": "2", "XO": "5", "X-": "3", "XX": "1"}, "operation": "decode", "points": 225, "question": "<p>Decode this quote which has been encoded using the Morbit cipher. OO,OX,X-,XO,XX matches to 4,9,3,5,1.</p>", "hint": "123456"}}