{"TEST.0": {"timed": 0, "count": 20, "questions": [1, 2, 3, 4, 5, 6, 7, 8, 9, 10, 11, 12, 13, 14, 15, 16, 17, 18, 19, 20], "title": "okoneword", "useCustomHeader": false, "customHeader": "", "testtype": "cstate"}, "CIPHER.0": {"cipherString": "Do your work with your whole heart, and you will succeed - there's so little competition.", "encodeType": "random", "offset": 1, "shift": 1, "offset2": 1, "keyword": "", "keyword2": "", "alphabetSource": "ABCDEFGHIJKLMNOPQRSTUVWXYZ", "alphabetDest": "YKHSLPCEWTIGDAVJNBQMOZFURX", "curlang": "en", "replacement": {"A": "Y", "B": "K", "C": "H", "D": "S", "E": "L", "F": "P", "G": "C", "H": "E", "I": "W", "J": "T", "K": "I", "L": "G", "M": "D", "N": "A", "O": "V", "P": "J", "Q": "N", "R": "B", "S": "Q", "T": "M", "U": "O", "V": "Z", "W": "F", "X": "U", "Y": "R", "Z": "X"}, "editEntry": "0", "cipherType": "aristocrat", "question": "<p>Solve this aristocrat.</p>", "points": 250}, "CIPHER.1": {"cipherString": "Autumn wins you best by this its mute appeal to sympathy for its decay.", "encodeType": "random", "offset": 1, "shift": 1, "offset2": 1, "keyword": "", "keyword2": "", "alphabetSource": "ABCDEFGHIJKLMNOPQRSTUVWXYZ", "alphabetDest": "DSITXWJRBAEYHGQVMCLZONUFPK", "curlang": "en", "replacement": {"A": "D", "B": "S", "C": "I", "D": "T", "E": "X", "F": "W", "G": "J", "H": "R", "I": "B", "J": "A", "K": "E", "L": "Y", "M": "H", "N": "G", "O": "Q", "P": "V", "Q": "M", "R": "C", "S": "L", "T": "Z", "U": "O", "V": "N", "W": "U", "X": "F", "Y": "P", "Z": "K"}, "editEntry": "0", "cipherType": "aristocrat", "question": "<p>Solve this aristocrat.</p>", "points": 250}, "CIPHER.2": {"cipherString": "I use the rules to frustrate the law. But I didn't set up the ground rules.", "encodeType": "random", "offset": 1, "shift": 1, "offset2": 1, "keyword": "", "keyword2": "", "alphabetSource": "ABCDEFGHIJKLMNOPQRSTUVWXYZ", "alphabetDest": "CDNZMXIRUAJGKBEQSWPLVFHOTY", "curlang": "en", "replacement": {"A": "C", "B": "D", "C": "N", "D": "Z", "E": "M", "F": "X", "G": "I", "H": "R", "I": "U", "J": "A", "K": "J", "L": "G", "M": "K", "N": "B", "O": "E", "P": "Q", "Q": "S", "R": "W", "S": "P", "T": "L", "U": "V", "V": "F", "W": "H", "X": "O", "Y": "T", "Z": "Y"}, "editEntry": "1", "cipherType": "aristocrat", "question": "<p>Solve this aristocrat.</p>", "points": 250}, "CIPHER.3": {"cipherString": "Why worry about things you can\ufffdt control when you can keep yourself busy controlling the things that depend on you?", "encodeType": "random", "offset": 1, "shift": 1, "offset2": 1, "keyword": "", "keyword2": "", "alphabetSource": "ABCDEFGHIJKLMNOPQRSTUVWXYZ", "alphabetDest": "BTEJFZMYKXPDVURLGCWHANSIOQ", "curlang": "en", "replacement": {"A": "B", "B": "T", "C": "E", "D": "J", "E": "F", "F": "Z", "G": "M", "H": "Y", "I": "K", "J": "X", "K": "P", "L": "D", "M": "V", "N": "U", "O": "R", "P": "L", "Q": "G", "R": "C", "S": "W", "T": "H", "U": "A", "V": "N", "W": "S", "X": "I", "Y": "O", "Z": "Q"}, "editEntry": "2", "cipherType": "aristocrat", "question": "<p>Solve this aristocrat.</p>", "points": 250}, "CIPHER.4": {"cipherString": "I mean, gosh, my first tours I ever did were with the Ramones and Iggy Pop and Love & Rockets.", "encodeType": "random", "offset": 1, "shift": 1, "offset2": 1, "keyword": "", "keyword2": "", "alphabetSource": "ABCDEFGHIJKLMNOPQRSTUVWXYZ", "alphabetDest": "UYZHQJPILTNVWDBXOFGMACKSRE", "curlang": "en", "replacement": {"A": "U", "B": "Y", "C": "Z", "D": "H", "E": "Q", "F": "J", "G": "P", "H": "I", "I": "L", "J": "T", "K": "N", "L": "V", "M": "W", "N": "D", "O": "B", "P": "X", "Q": "O", "R": "F", "S": "G", "T": "M", "U": "A", "V": "C", "W": "K", "X": "S", "Y": "R", "Z": "E"}, "editEntry": "3", "cipherType": "aristocrat", "question": "<p>Solve this aristocrat.</p>", "points": 250}, "CIPHER.5": {"cipherString": "His hatred of snobs was a derivative of his snobbishness, but made the simpletons (in other words, everyone) believe that he was immune from snobbishness.", "encodeType": "random", "offset": 1, "shift": 1, "offset2": 1, "keyword": "", "keyword2": "", "alphabetSource": "ABCDEFGHIJKLMNOPQRSTUVWXYZ", "alphabetDest": "TCSNIQVPRFZXWDJBMLYAKOGEUH", "curlang": "en", "replacement": {"A": "T", "B": "C", "C": "S", "D": "N", "E": "I", "F": "Q", "G": "V", "H": "P", "I": "R", "J": "F", "K": "Z", "L": "X", "M": "W", "N": "D", "O": "J", "P": "B", "Q": "M", "R": "L", "S": "Y", "T": "A", "U": "K", "V": "O", "W": "G", "X": "E", "Y": "U", "Z": "H"}, "editEntry": "4", "cipherType": "aristocrat", "question": "<p>Solve this aristocrat.</p>", "points": 250}, "CIPHER.6": {"cipherString": "Being the richest man in the cemetery doesn't matter to me. Going to bed at night saying we've done something wonderful, that's what matters to me.", "encodeType": "random", "offset": 1, "shift": 1, "offset2": 1, "keyword": "", "keyword2": "", "alphabetSource": "ABCDEFGHIJKLMNOPQRSTUVWXYZ", "alphabetDest": "UHXKPQAVYSJRIMZBLEDGCOFNTW", "curlang": "en", "replacement": {"A": "U", "B": "H", "C": "X", "D": "K", "E": "P", "F": "Q", "G": "A", "H": "V", "I": "Y", "J": "S", "K": "J", "L": "R", "M": "I", "N": "M", "O": "Z", "P": "B", "Q": "L", "R": "E", "S": "D", "T": "G", "U": "C", "V": "O", "W": "F", "X": "N", "Y": "T", "Z": "W"}, "editEntry": "5", "cipherType": "aristocrat", "question": "<p>Solve this aristocrat.</p>", "points": 250}, "CIPHER.7": {"cipherString": "When people are free to do as they please, they usually imitate each other.", "encodeType": "random", "offset": 1, "shift": 1, "offset2": 1, "keyword": "", "keyword2": "", "alphabetSource": "ABCDEFGHIJKLMNOPQRSTUVWXYZ", "alphabetDest": "HWAQDNFZXYMELIPRGVCUJOTKBS", "curlang": "en", "replacement": {"A": "H", "B": "W", "C": "A", "D": "Q", "E": "D", "F": "N", "G": "F", "H": "Z", "I": "X", "J": "Y", "K": "M", "L": "E", "M": "L", "N": "I", "O": "P", "P": "R", "Q": "G", "R": "V", "S": "C", "T": "U", "U": "J", "V": "O", "W": "T", "X": "K", "Y": "B", "Z": "S"}, "editEntry": "6", "cipherType": "aristocrat", "question": "<p>Solve this aristocrat.</p>", "points": 250}, "CIPHER.8": {"cipherString": "My father always used to say that when you die, if you've got five real friends, then you've had a great life.", "encodeType": "random", "offset": 1, "shift": 1, "offset2": 1, "keyword": "", "keyword2": "", "alphabetSource": "ABCDEFGHIJKLMNOPQRSTUVWXYZ", "alphabetDest": "FAHBDVQERIJTSLMZGXWUOKCPNY", "curlang": "en", "replacement": {"A": "F", "B": "A", "C": "H", "D": "B", "E": "D", "F": "V", "G": "Q", "H": "E", "I": "R", "J": "I", "K": "J", "L": "T", "M": "S", "N": "L", "O": "M", "P": "Z", "Q": "G", "R": "X", "S": "W", "T": "U", "U": "O", "V": "K", "W": "C", "X": "P", "Y": "N", "Z": "Y"}, "editEntry": "7", "cipherType": "aristocrat", "question": "<p>Solve this aristocrat.</p>", "points": 250}, "CIPHER.9": {"cipherString": "Everything that irritates us about others can lead us to an understanding about ourselves.", "encodeType": "random", "offset": 1, "shift": 1, "offset2": 1, "keyword": "", "keyword2": "", "alphabetSource": "ABCDEFGHIJKLMNOPQRSTUVWXYZ", "alphabetDest": "GTFYCZRNAOEBVWHIDMKJQUXSPL", "curlang": "en", "replacement": {"A": "G", "B": "T", "C": "F", "D": "Y", "E": "C", "F": "Z", "G": "R", "H": "N", "I": "A", "J": "O", "K": "E", "L": "B", "M": "V", "N": "W", "O": "H", "P": "I", "Q": "D", "R": "M", "S": "K", "T": "J", "U": "Q", "V": "U", "W": "X", "X": "S", "Y": "P", "Z": "L"}, "editEntry": "8", "cipherType": "aristocrat", "question": "<p>Solve this aristocrat.</p>", "points": 250}, "CIPHER.10": {"cipherString": "They who dream by day are cognizant of many things which escape those who dream only by night.", "encodeType": "random", "offset": 1, "shift": 1, "offset2": 1, "keyword": "", "keyword2": "", "alphabetSource": "ABCDEFGHIJKLMNOPQRSTUVWXYZ", "alphabetDest": "HOKCUZREBALXYTINJPWVQSMDGF", "curlang": "en", "replacement": {"A": "H", "B": "O", "C": "K", "D": "C", "E": "U", "F": "Z", "G": "R", "H": "E", "I": "B", "J": "A", "K": "L", "L": "X", "M": "Y", "N": "T", "O": "I", "P": "N", "Q": "J", "R": "P", "S": "W", "T": "V", "U": "Q", "V": "S", "W": "M", "X": "D", "Y": "G", "Z": "F"}, "editEntry": "9", "cipherType": "aristocrat", "question": "<p>Solve this aristocrat.</p>", "points": 250}, "CIPHER.11": {"cipherString": "But pleasures are like poppies spread, You seize the flow'r, its bloom is shed.", "encodeType": "random", "offset": 1, "shift": 1, "offset2": 1, "keyword": "", "keyword2": "", "alphabetSource": "ABCDEFGHIJKLMNOPQRSTUVWXYZ", "alphabetDest": "DVUMBZYPQLCFWHKAISEOGTRJNX", "curlang": "en", "replacement": {"A": "D", "B": "V", "C": "U", "D": "M", "E": "B", "F": "Z", "G": "Y", "H": "P", "I": "Q", "J": "L", "K": "C", "L": "F", "M": "W", "N": "H", "O": "K", "P": "A", "Q": "I", "R": "S", "S": "E", "T": "O", "U": "G", "V": "T", "W": "R", "X": "J", "Y": "N", "Z": "X"}, "editEntry": "10", "cipherType": "aristocrat", "question": "<p>Solve this aristocrat.</p>", "points": 250}, "CIPHER.12": {"cipherString": "There is no need for nuclear. The world can be powered by wind, water and sun alone.", "encodeType": "random", "offset": 1, "shift": 1, "offset2": 1, "keyword": "", "keyword2": "", "alphabetSource": "ABCDEFGHIJKLMNOPQRSTUVWXYZ", "alphabetDest": "WVHONDCPXBYIEZJKLSFMTUGRAQ", "curlang": "en", "replacement": {"A": "W", "B": "V", "C": "H", "D": "O", "E": "N", "F": "D", "G": "C", "H": "P", "I": "X", "J": "B", "K": "Y", "L": "I", "M": "E", "N": "Z", "O": "J", "P": "K", "Q": "L", "R": "S", "S": "F", "T": "M", "U": "T", "V": "U", "W": "G", "X": "R", "Y": "A", "Z": "Q"}, "editEntry": "11", "cipherType": "aristocrat", "question": "<p>Solve this aristocrat.</p>", "points": 250}, "CIPHER.13": {"cipherString": "Men and nations behave wisely once they have exhausted all the other alternatives.", "encodeType": "random", "offset": 1, "shift": 1, "offset2": 1, "keyword": "", "keyword2": "", "alphabetSource": "ABCDEFGHIJKLMNOPQRSTUVWXYZ", "alphabetDest": "JMRGIUYFCXNESBDTZKWOVQLAPH", "curlang": "en", "replacement": {"A": "J", "B": "M", "C": "R", "D": "G", "E": "I", "F": "U", "G": "Y", "H": "F", "I": "C", "J": "X", "K": "N", "L": "E", "M": "S", "N": "B", "O": "D", "P": "T", "Q": "Z", "R": "K", "S": "W", "T": "O", "U": "V", "V": "Q", "W": "L", "X": "A", "Y": "P", "Z": "H"}, "editEntry": "12", "cipherType": "aristocrat", "question": "<p>Solve this aristocrat.</p>", "points": 250}, "CIPHER.14": {"cipherString": "You can't start worrying about what's going to happen. You get spastic enough worrying about what's happening now.", "encodeType": "random", "offset": 1, "shift": 1, "offset2": 1, "keyword": "", "keyword2": "", "alphabetSource": "ABCDEFGHIJKLMNOPQRSTUVWXYZ", "alphabetDest": "LZSWXGUPFAVTJBIEYKMDOHCQRN", "curlang": "en", "replacement": {"A": "L", "B": "Z", "C": "S", "D": "W", "E": "X", "F": "G", "G": "U", "H": "P", "I": "F", "J": "A", "K": "V", "L": "T", "M": "J", "N": "B", "O": "I", "P": "E", "Q": "Y", "R": "K", "S": "M", "T": "D", "U": "O", "V": "H", "W": "C", "X": "Q", "Y": "R", "Z": "N"}, "editEntry": "13", "cipherType": "aristocrat", "question": "<p>Solve this aristocrat.</p>", "points": 250}, "CIPHER.15": {"cipherString": "If your religion doesn't respect the rights of other religions, it is lacking something.", "encodeType": "random", "offset": 1, "shift": 1, "offset2": 1, "keyword": "", "keyword2": "", "alphabetSource": "ABCDEFGHIJKLMNOPQRSTUVWXYZ", "alphabetDest": "HXPIZQCKGLTDYBMOFWENAJUSVR", "curlang": "en", "replacement": {"A": "H", "B": "X", "C": "P", "D": "I", "E": "Z", "F": "Q", "G": "C", "H": "K", "I": "G", "J": "L", "K": "T", "L": "D", "M": "Y", "N": "B", "O": "M", "P": "O", "Q": "F", "R": "W", "S": "E", "T": "N", "U": "A", "V": "J", "W": "U", "X": "S", "Y": "V", "Z": "R"}, "editEntry": "14", "cipherType": "aristocrat", "question": "<p>Solve this aristocrat.</p>", "points": 250}, "CIPHER.16": {"cipherString": "The Irish Republican Army has kept every commitment made by its leadership.", "encodeType": "random", "offset": 1, "shift": 1, "offset2": 1, "keyword": "", "keyword2": "", "alphabetSource": "ABCDEFGHIJKLMNOPQRSTUVWXYZ", "alphabetDest": "VKBJPTNUGLFHWCDMAZRIXYQOSE", "curlang": "en", "replacement": {"A": "V", "B": "K", "C": "B", "D": "J", "E": "P", "F": "T", "G": "N", "H": "U", "I": "G", "J": "L", "K": "F", "L": "H", "M": "W", "N": "C", "O": "D", "P": "M", "Q": "A", "R": "Z", "S": "R", "T": "I", "U": "X", "V": "Y", "W": "Q", "X": "O", "Y": "S", "Z": "E"}, "editEntry": "15", "cipherType": "aristocrat", "question": "<p>Solve this aristocrat.</p>", "points": 250}, "CIPHER.17": {"cipherString": "Sharing the stage while singing my songs was a bit of a daunting prospect.", "encodeType": "random", "offset": 1, "shift": 1, "offset2": 1, "keyword": "", "keyword2": "", "alphabetSource": "ABCDEFGHIJKLMNOPQRSTUVWXYZ", "alphabetDest": "YJXCFHVOABZNPESIUWQMDTGKLR", "curlang": "en", "replacement": {"A": "Y", "B": "J", "C": "X", "D": "C", "E": "F", "F": "H", "G": "V", "H": "O", "I": "A", "J": "B", "K": "Z", "L": "N", "M": "P", "N": "E", "O": "S", "P": "I", "Q": "U", "R": "W", "S": "Q", "T": "M", "U": "D", "V": "T", "W": "G", "X": "K", "Y": "L", "Z": "R"}, "editEntry": "16", "cipherType": "aristocrat", "question": "<p>Solve this aristocrat.</p>", "points": 250}, "CIPHER.18": {"cipherString": "A person who has not done one half his day's work by ten o clock, runs a chance of leaving the other half undone.", "encodeType": "random", "offset": 1, "shift": 1, "offset2": 1, "keyword": "", "keyword2": "", "alphabetSource": "ABCDEFGHIJKLMNOPQRSTUVWXYZ", "alphabetDest": "QLGRSZNVFHTDWPCMUIYBEAXJOK", "curlang": "en", "replacement": {"A": "Q", "B": "L", "C": "G", "D": "R", "E": "S", "F": "Z", "G": "N", "H": "V", "I": "F", "J": "H", "K": "T", "L": "D", "M": "W", "N": "P", "O": "C", "P": "M", "Q": "U", "R": "I", "S": "Y", "T": "B", "U": "E", "V": "A", "W": "X", "X": "J", "Y": "O", "Z": "K"}, "editEntry": "17", "cipherType": "aristocrat", "question": "<p>Solve this aristocrat.</p>", "points": 250}, "CIPHER.19": {"cipherString": "I've always taken 'The Wizard of Oz' very seriously, you know. I believe in the idea of the rainbow. And I've spent my entire life trying to get over it.", "encodeType": "random", "offset": 1, "shift": 1, "offset2": 1, "keyword": "", "keyword2": "", "alphabetSource": "ABCDEFGHIJKLMNOPQRSTUVWXYZ", "alphabetDest": "JUPZIRNVSXHAODMWBTEGQLCFKY", "curlang": "en", "replacement": {"A": "J", "B": "U", "C": "P", "D": "Z", "E": "I", "F": "R", "G": "N", "H": "V", "I": "S", "J": "X", "K": "H", "L": "A", "M": "O", "N": "D", "O": "M", "P": "W", "Q": "B", "R": "T", "S": "E", "T": "G", "U": "Q", "V": "L", "W": "C", "X": "F", "Y": "K", "Z": "Y"}, "editEntry": "18", "cipherType": "aristocrat", "question": "<p>Solve this aristocrat.</p>", "points": 250}, "CIPHER.20": {"cipherString": "My little son, Atticus, desperately needs his dad and I haven't been there for him... and that's sad.", "encodeType": "random", "offset": 1, "shift": 1, "offset2": 1, "keyword": "", "keyword2": "", "alphabetSource": "ABCDEFGHIJKLMNOPQRSTUVWXYZ", "alphabetDest": "IONQMGFRDZHCLEJXWYVAKPBUTS", "curlang": "en", "replacement": {"A": "I", "B": "O", "C": "N", "D": "Q", "E": "M", "F": "G", "G": "F", "H": "R", "I": "D", "J": "Z", "K": "H", "L": "C", "M": "L", "N": "E", "O": "J", "P": "X", "Q": "W", "R": "Y", "S": "V", "T": "A", "U": "K", "V": "P", "W": "B", "X": "U", "Y": "T", "Z": "S"}, "editEntry": "19", "cipherType": "aristocrat", "question": "<p>Solve this aristocrat.</p>", "points": 250}}